{"name":"Simplemotioneffects","tagline":"Simply add UIView Motion Effects in a single line!","body":"# SimpleMotionEffects\r\n\r\nThis **UIView Category** provides the most simple API to create motion effects faster with only a single line of code.\r\n\r\n![Screenshot](https://github.com/jaydee3/SimpleMotionEffects/raw/master/gfx/screenshot.png)\r\n\r\n## Installation\r\n\r\nAdd the pod `pod 'SimpleMotionEffects'`,  \r\nor add the `UIView+SimpleMotionEffects.{h,m}` files manually to your project.\r\n\r\n\r\n## Usage\r\n\r\n1. Import the header `#import \"UIView+SimpleMotionEffects.h\"`\r\n2. Use any of the following methods on any UIView.\r\n\r\nJust specify how much a view should move at maximum on both axes, when tilting:\r\n\r\n\t- (void)addMotionEffectWithMovement:(CGPoint)movement;\r\n\t\r\nOr specify, how much a view should move on both axes reacting to horizontalTilt oder verticalTilt only:\r\n\t\r\n\t- (void)addMotionEffectOnHorizontalTilt:(CGPoint)horizontalMovement\r\n\t                         onVerticalTilt:(CGPoint)verticalMovement;\r\n\r\nOr for more granular settings:\r\n\r\n\t- (void)addMotionEffectWithType:(UIInterpolatingMotionEffectType)type\r\n\t                        keyPath:(NSString*)keyPath\r\n\t                          value:(CGFloat)value;\r\n\t\r\n\t- (void)addMotionEffectWithType:(UIInterpolatingMotionEffectType)type\r\n\t                        keyPath:(NSString*)keyPath\r\n\t                       minValue:(CGFloat)minValue\r\n\t                       maxValue:(CGFloat)maxValue;\r\n\r\n## Twitter\r\n\r\nI'm [@jaydee3](http://twitter.com/jaydee3) on Twitter.","google":"","note":"Don't delete this file! It's used internally to help with page regeneration."}